[{"complete":"HackerspaceSG, 344B King George's Avenue, King George's Building, 208576, Singapore","all":["Hackerspace.SG, 344B King George's Ave, King George's Building, Singapore","344B King George's Rd, 208576","Hackerspace, 344B King George's Avenue, Singapore","Hackerspace, 344B King George's Building, Singapore","HackerspaceSG, 344B King George's Avenue, King George's Building, 208576, Singapore","HackerspaceSG, 344B King George's Avenue, King George's Building, Singapore 208576","HackerspaceSG, 344B King George's Avenue, Singapore 208576"],"n":32,"groups":["HASKELL.SG","SingaporeJS","HackerspaceSG Awesome Talks","3D For Everyone Meetup","WordPress Singapore","Hackware","The Singapore Linux Meetup Group","PUGS (Postgres Users Group Singapore)","FOSSASIA Singapore OpenXLab Meetup","Singapore Magento User Group","HackerspaceSG","Papers We Love Singapore","Engineers.SG","Subhransu Behera"],"latitude":1.31042,"longitude":103.862409},{"complete":"Skyscanner, 39 Robinson Road, #09-01 Robinson Point, Singapore 068911","all":["SkyScanner Ltd, 39 Robinson Road #09-01 Robinson Point, Singapore","Skyscanner, 39 Robinson Road, #09-01 Robinson Point, Singapore 068911"],"n":10,"groups":["Ruby Tea Party  (SG)","Singapore Ruby Group","PyData Singapore"],"latitude":1.279644,"longitude":103.849487},{"complete":"Barclays, 10 Marina Boulevard, #23-01, Marina Bay Financial Centre Tower 2, Singapore","all":["Barclays, 10 Marina Boulevard, #23-01, Marina Bay Financial Centre Tower 2, Singapore"],"n":8,"groups":["Agile Singapore","Live Agile Workshop & Forum Group"],"latitude":1.2792463,"longitude":103.8541121},{"complete":"Toa Payoh Public Library, 6 Toa Payoh Central, Singapore 319191","all":["Toa Payoh Public Library","Toa Payoh Public Library, 6 Toa Payoh Central, Singapore 319191"],"n":12,"groups":["Creative Crew Singapore"],"latitude":1.333791,"longitude":103.850514},{"complete":"Microsoft Auditorium (Singapore), One Marina Boulevard, Level 21 Auditorium, Singapore 018989 ","all":["Microsoft Auditorium (Singapore), One Marina Boulevard, Level 21 Auditorium, Singapore 018989 "],"n":17,"groups":["R User Group - Singapore (RUGS)",".NET Developers Singapore","Microsoft User Groups (Singapore)","SingaporeJS","DataScience SG","Visual Studio ALM Singapore","Singapore Xamarin User group"],"latitude":1.2808099,"longitude":103.8542337},{"complete":"A*START Central, #05-01, JTC Launchpad, Blk 79, Ayer Rajah Crescent, Opposite to Fusionopolis, Singapore 139955","all":["Plugin@Blk71, 71 Ayer Rajah Crescent,  #02-18, Singapore 139951","NUS Enterprise@Blk71, 71 Ayer Rajah Crescent, #02-01, Singapore 139951","NUS Enterprise@Blk71 71 Ayer Rajah Crescent, #02-01, Singapore 139951","Heardable, Block 71, #01-17/18, 71 Ayer Rajah Crescent, Singapore","TH, Ayer Rajah Crescent, Singapore","Lithan Accelerator, Launchpad@one-north Blk 79, Ayer Rajah Crescent #04-04 Singapore 139955 ","NUS Enterprise at Blk 71, 71 Ayer Rajah Crescent,  #02-01","Sonoport (Blk 71 Ayer Rajah Crescent, #04-18, Ayer Rajah Industrial Estate, Singapore 139951)","Carousell, 71 Ayer Rajah Crescent, #05-14 Singapore 139951","03-26, block 71, Ayer Rajah Crescent, Singapore","Carousell HQ, Blk 71 Ayer Rajah Crescent #03-14, Singapore 139951","Blk 71 Ayer Rajah Crescent #02-01, Singapore 139951","Bash, 79 Ayer Rajah Crescent, Singapore","Life.SREDA Venture Capital Firm, Blk 79, Ayer Rajah Crescent #05-08, Singapore","NUS Enterprise@Blk71, 71 Ayer Rajah Crescent, #02 - 01, Singapore 139951 null","Blk 71 Ayer Rajah Crescent #05-14, , Singapore","NUS Plug-In@Blk71 (the NEW Co-Working Space), 71 Ayer Rajah Crescent, #02-01, 139951, Singapore, Singapore","A*START Central, #05-01, JTC Launchpad, Blk 79, Ayer Rajah Crescent, Opposite to Fusionopolis, Singapore 139955","A*START Central, #05-01, JTC Launchpad, Blk 79, Ayer Rajah Crescent, Opp Fusionopolis, Singapore 139955"],"n":42,"groups":["Meteor Singapore","Bluemix Singapore","Hackware","Singapore Coding Meetup","Asia VR Association - Singapore Virtual Reality meetup","Ethereum Singapore","AsiaVR Association - Singapore Virtual Reality meetup","PUGS (Postgres Users Group Singapore)","Android In Asia","Front End Developers Singapore","Singapore Ruby Group","Data Night Singapore","SingaporeCSS","Carousell","AsiaVR Association - Singapore Virtual Reality Meetup Group","National Supercomputing Centre","PyLadies SG","HackerNest Singapore Tech Socials","Google Cloud Platform User Group Singapore","A*PECSS and A*STARTCentral"],"latitude":1.298131,"longitude":103.788034},{"complete":"Thoughtworks, 87B Amoy Street #04, Singapore 069906, Singapore","all":["Thought Works,  Level 3, 87B Amoy Street, 069906, Singapore","Thoughtworks, 87B Amoy Street #04, Singapore 069906, Singapore","ThoughtWorks, 87B Amoy Street #03/04, Singapore 069906","ThoughtWorks office, 87B Amoy Street, Level 3, Singapore","ThoughtWorks, 87B Amoy St, Singapore"],"n":20,"groups":["Null Singapore - The Open Security Community","DevOps Singapore","DataKind SG","Singapore Scala Programmers","GoSG","Singapore Clojure Meetup","Singapore Software QA Meetup","Singapore Elixir Meetup","DevSecOps Singapore"],"latitude":1.280945,"longitude":103.847069},{"complete":"Neo Innovation , 53A Craig Road , 089691, Singapore","all":["Neo Office, 53A Craig Road, Singapore","Neo Innovation , 53A Craig Road , 089691, Singapore","Neo Innovation, 53A Craig Road, Singapore"],"n":6,"groups":["HASKELL.SG","Singapore Clojure Meetup","Singapore Product Management Meetup"],"latitude":1.27777,"longitude":103.8423509},{"complete":"PayPal office in Suntec, 5 Temasek Blvd, #09-01 Suntec Tower Five, 038985 Nearest Mrt:Promenade(Yellow Line), Singapore","all":["PayPal office in Suntec, 5 Temasek Blvd, #09-01 Suntec Tower Five, 038985 Nearest Mrt:Promenade(Yellow Line), Singapore"],"n":14,"groups":["Singapore Spring User Group","Singapore iOS Dev Scout Meetup","Docker Singapore","Hackware"],"latitude":1.2946917,"longitude":103.8578323},{"complete":"ArtScience Museum","all":["ArtScience Museum"],"n":25,"groups":["ArtScience Museum"],"latitude":1.2862737,"longitude":103.8592661},{"complete":"Tim & Wei's Residence, 244A Tanjong Katong Road, Singapore","all":["Tim & Wei's Residence, 244A Tanjong Katong Road, Singapore"],"n":22,"groups":["SingaporeJS"],"latitude":1.306474,"longitude":103.895674},{"complete":"Sandcrawler, 1 Fusionopolis View #08-01 S138577, Singapore","all":["Sandcrawler, 1 Fusionopolis View #08-01 S138577, Singapore"],"n":7,"groups":["Singapore Ruby Group","Agile Singapore"],"latitude":1.2996411,"longitude":103.7893207},{"complete":"Medical Alumni Association","all":["Medical Alumni Association"],"n":5,"groups":["Singapore Amateur Radio Transmitting Society"],"latitude":1.282396,"longitude":103.836024},{"complete":"Hive@Sandcrawler, 1 Fusionopolis View #08-01, Singapore","all":["Hive@Sandcrawler, 1 Fusionopolis View #08-01, Singapore"],"n":8,"groups":["ReactJS Singapore","DataScience SG","Singapore Software QA Meetup"],"latitude":1.2996411,"longitude":103.7893207},{"complete":"Akamai Singapore office, 1 Raffles Place, #16-61, One Raffles Place Tower 2, Singapore 048616","all":["Akamai Singapore office, 1 Raffles Place, #16-61, One Raffles Place Tower 2, Singapore 048616"],"n":7,"groups":["The Singapore Security Meetup Group","Null Singapore - The Open Security Community"],"latitude":1.2842969,"longitude":103.8510638},{"complete":"Science Centre Singapore","all":["Science Centre Singapore"],"n":10,"groups":["Maker Faire Singapore"],"latitude":1.33023,"longitude":103.7383967},{"complete":"PayPal, 5 Temasek Blvd, #09-01 Suntec Tower Five, 038985, Singapore","all":["PayPal, 5 Temasek Blvd, #09-01 Suntec Tower Five, 038985, Singapore"],"n":10,"groups":["Singapore Ruby Group","Grumpy Gits SG","Agile Singapore","DataScience SG","Singapore Python User Group","Singapore Creative Coding Meetup","Singapore MusicTech Meetup","SingaporeCSS"],"latitude":1.2946917,"longitude":103.8578323},{"complete":"Paypal at Suntec , 5 Temasek Blvd, #07-01 Suntec Tower Five, Nearest Mrt:Promenade(Yellow Line), Singapore","all":["Paypal at Suntec , 5 Temasek Blvd, #07-01 Suntec Tower Five, Nearest Mrt:Promenade(Yellow Line), Singapore"],"n":5,"groups":["Singapore iOS Dev Scout Meetup","Singapore Geek Girls","Singapore CSS","Singapore Clojure Meetup","Bitcoins in Singapore"],"latitude":1.2946917,"longitude":103.8578323},{"complete":"SPH Auditorium, 1000 Toa Payoh North, News Centre, Singapore 318994 ","all":["SPH Auditorium, 1000 Toa Payoh North, News Centre, Singapore 318994 ","ST Innovation Lab - SPH, 1000 Toa Payoh North, Singapore","SPH News Centre, 1000 Toa Payoh North, Singapore","SPH News Center (T8.2/T8.3), 1000 Toa Payoh North Singapore 318994"],"n":5,"groups":["Hacks/Hackers Singapore","SingaporeJS","Agile Singapore"],"latitude":1.342617,"longitude":103.848429},{"complete":"Rakuten Crimson House, 138 Market Street, Lvl 32, CapitaGreen, 048946, Singapore","all":["Rakuten Crimson House, 138 Market Street, Lvl 32, CapitaGreen, 048946, Singapore","Viki, 138 Market Street, #32-01 (Capitagreen building), Singapore","Rakuten Viki, 138 Market Street, Lv.32, Singapore"],"n":7,"groups":["DesignDojo Singapore","Design Dojo Singapore","Docker Singapore","SingaporeCSS"],"latitude":1.352083,"longitude":103.819836},{"complete":"Singapore, North, East, South, West","all":["Singapore, North, East, South, West"],"n":5,"groups":["Null Singapore - The Open Security Community"],"latitude":1.352083,"longitude":103.819836},{"complete":"Pivotal Labs Singapore, 53A Craig Road","all":["Pivotal Labs Singapore, 53A Craig Road","Pivotal Singapore Labs, 53 Craig Road"],"n":8,"groups":["HASKELL.SG","Singapore Ruby Group","Singapore Djangonauts","Singapore Cloud Foundry Meetup","Singapore Algorithmic Trading Meetup"],"latitude":1.27777,"longitude":103.8423509},{"complete":"ArtScience Museum, 10 Bayfront Avenue, Singapore 018956","all":["ArtScience Museum, 10 Bayfront Avenue, Singapore 018956"],"n":6,"groups":["ArtScience Museum"],"latitude":1.2863163,"longitude":103.859275},{"complete":"Lowercase, 1 McNally St, Blk D #01-01, Singapore","all":["Lowercase, 1 McNally St, Blk D #01-01, Singapore"],"n":10,"groups":["Singapore Scala Programmers"],"latitude":1.3025743,"longitude":103.8513396}]