{"meta":{"generated_at":"2017-04-19T18:03:23.643Z","location":"Singapore","total_repos":17},"repos":[{"name":"status-react","html_url":"https://github.com/status-im/status-react","description":"a free (libre) open source, mobile OS for Ethereum","pushed_at":"2017-04-19T18:02:37Z","updated_at":"2017-04-19T15:41:12Z","formatted_time":"in an hour","language":"Clojure","stargazers_count":267,"forks_count":85,"open_issues_count":163,"size":26917,"type":"Organization","owner":{"login":"status-im","avatar_url":"https://avatars2.githubusercontent.com/u/11767950?v=3","html_url":"https://github.com/status-im"},"contributors":[{"login":"rasom","html_url":"https://github.com/rasom","contributions":547},{"login":"virvar","html_url":"https://github.com/virvar","contributions":213},{"login":"jarradh","html_url":"https://github.com/jarradh","contributions":149},{"login":"adrian-tiberius","html_url":"https://github.com/adrian-tiberius","contributions":138},{"login":"alwx","html_url":"https://github.com/alwx","contributions":122},{"login":"michaelr524","html_url":"https://github.com/michaelr524","contributions":54},{"login":"flexsurfer","html_url":"https://github.com/flexsurfer","contributions":33},{"login":"GustavoNunes","html_url":"https://github.com/GustavoNunes","contributions":22},{"login":"rolandkofler","html_url":"https://github.com/rolandkofler","contributions":4},{"login":"coyotespike","html_url":"https://github.com/coyotespike","contributions":2},{"login":"ndrluis","html_url":"https://github.com/ndrluis","contributions":1},{"login":"auryn-macmillan","html_url":"https://github.com/auryn-macmillan","contributions":1},{"login":"dominicphillips","html_url":"https://github.com/dominicphillips","contributions":1},{"login":"erikzrekz","html_url":"https://github.com/erikzrekz","contributions":1},{"login":"neptox","html_url":"https://github.com/neptox","contributions":1},{"login":"agnivalent","html_url":"https://github.com/agnivalent","contributions":1},{"login":"harshjv","html_url":"https://github.com/harshjv","contributions":1},{"login":"mathvdh","html_url":"https://github.com/mathvdh","contributions":1},{"login":"MCRy","html_url":"https://github.com/MCRy","contributions":1},{"login":"Smokyish","html_url":"https://github.com/Smokyish","contributions":1},{"login":"tpatja","html_url":"https://github.com/tpatja","contributions":1},{"login":"TheHealthyCat","html_url":"https://github.com/TheHealthyCat","contributions":1},{"login":"SevenSwen","html_url":"https://github.com/SevenSwen","contributions":1},{"login":"viebel","html_url":"https://github.com/viebel","contributions":1},{"login":"mintheredonethat","html_url":"https://github.com/mintheredonethat","contributions":1},{"login":"greggdourgarian","html_url":"https://github.com/greggdourgarian","contributions":1},{"login":"johnmn3","html_url":"https://github.com/johnmn3","contributions":1},{"login":"madvas","html_url":"https://github.com/madvas","contributions":1},{"login":"tomkysar","html_url":"https://github.com/tomkysar","contributions":1},{"login":"dymnz","html_url":"https://github.com/dymnz","contributions":1}]},{"name":"deep-learning-workshop","html_url":"https://github.com/mdda/deep-learning-workshop","description":"Deep Learning Workshop : Including a VirtualBox VM with pre-configured Jupyter, Theano, Tensorflow, models and data","pushed_at":"2017-04-19T17:49:49Z","updated_at":"2017-04-18T17:21:53Z","formatted_time":"3 minutes ago","language":"Jupyter Notebook","stargazers_count":187,"forks_count":39,"open_issues_count":1,"size":17211,"type":"User","owner":{"login":"mdda","avatar_url":"https://avatars1.githubusercontent.com/u/362532?v=3","html_url":"https://github.com/mdda"},"contributors":[{"login":"mdda","html_url":"https://github.com/mdda","contributions":874}]},{"name":"cf-ui","html_url":"https://github.com/cloudflare/cf-ui","description":":gem: Cloudflare UI Framework","pushed_at":"2017-04-19T17:46:18Z","updated_at":"2017-04-17T16:07:05Z","formatted_time":"3 minutes ago","language":"JavaScript","stargazers_count":1184,"forks_count":59,"open_issues_count":17,"size":6890,"type":"Organization","owner":{"login":"cloudflare","avatar_url":"https://avatars0.githubusercontent.com/u/314135?v=3","html_url":"https://github.com/cloudflare"},"contributors":[{"login":"thejameskyle","html_url":"https://github.com/thejameskyle","contributions":192},{"login":"tajo","html_url":"https://github.com/tajo","contributions":185},{"login":"wyuenho","html_url":"https://github.com/wyuenho","contributions":68},{"login":"sejoker","html_url":"https://github.com/sejoker","contributions":38},{"login":"jwineman","html_url":"https://github.com/jwineman","contributions":21},{"login":"koddsson","html_url":"https://github.com/koddsson","contributions":18},{"login":"L1fescape","html_url":"https://github.com/L1fescape","contributions":6},{"login":"thellimist","html_url":"https://github.com/thellimist","contributions":5},{"login":"prestonp","html_url":"https://github.com/prestonp","contributions":3},{"login":"hturan","html_url":"https://github.com/hturan","contributions":3},{"login":"manatarms","html_url":"https://github.com/manatarms","contributions":3},{"login":"nkcmr","html_url":"https://github.com/nkcmr","contributions":3},{"login":"marksteyn","html_url":"https://github.com/marksteyn","contributions":2},{"login":"akenn","html_url":"https://github.com/akenn","contributions":1},{"login":"aweary","html_url":"https://github.com/aweary","contributions":1},{"login":"jculvey","html_url":"https://github.com/jculvey","contributions":1},{"login":"plumlee","html_url":"https://github.com/plumlee","contributions":1},{"login":"toekneestuck","html_url":"https://github.com/toekneestuck","contributions":1}]},{"name":"nativefier","html_url":"https://github.com/jiahaog/nativefier","description":"Make any web page a desktop application","pushed_at":"2017-04-19T17:37:22Z","updated_at":"2017-04-19T12:37:36Z","formatted_time":"3 minutes ago","language":"JavaScript","stargazers_count":9904,"forks_count":427,"open_issues_count":67,"size":4304,"type":"User","owner":{"login":"jiahaog","avatar_url":"https://avatars0.githubusercontent.com/u/7111741?v=3","html_url":"https://github.com/jiahaog"},"contributors":[{"login":"jiahaog","html_url":"https://github.com/jiahaog","contributions":430},{"login":"maxogden","html_url":"https://github.com/maxogden","contributions":74},{"login":"zweicoder","html_url":"https://github.com/zweicoder","contributions":17},{"login":"malept","html_url":"https://github.com/malept","contributions":11},{"login":"mafintosh","html_url":"https://github.com/mafintosh","contributions":9},{"login":"jsdnxx","html_url":"https://github.com/jsdnxx","contributions":9},{"login":"priezz","html_url":"https://github.com/priezz","contributions":7},{"login":"ronjouch","html_url":"https://github.com/ronjouch","contributions":6},{"login":"garymoon","html_url":"https://github.com/garymoon","contributions":5},{"login":"kfranqueiro","html_url":"https://github.com/kfranqueiro","contributions":4},{"login":"sindresorhus","html_url":"https://github.com/sindresorhus","contributions":3},{"login":"Rameshv","html_url":"https://github.com/Rameshv","contributions":3},{"login":"radarhere","html_url":"https://github.com/radarhere","contributions":2},{"login":"BugiDev","html_url":"https://github.com/BugiDev","contributions":2},{"login":"contra","html_url":"https://github.com/contra","contributions":2},{"login":"shama","html_url":"https://github.com/shama","contributions":2},{"login":"zaggino","html_url":"https://github.com/zaggino","contributions":2},{"login":"mattchue","html_url":"https://github.com/mattchue","contributions":2},{"login":"rohmanhm","html_url":"https://github.com/rohmanhm","contributions":2},{"login":"stefanbuck","html_url":"https://github.com/stefanbuck","contributions":2},{"login":"lexelby","html_url":"https://github.com/lexelby","contributions":2},{"login":"taiyoslime","html_url":"https://github.com/taiyoslime","contributions":2},{"login":"thomsbg","html_url":"https://github.com/thomsbg","contributions":1},{"login":"brunoqueiros","html_url":"https://github.com/brunoqueiros","contributions":1},{"login":"chentsulin","html_url":"https://github.com/chentsulin","contributions":1},{"login":"chmac","html_url":"https://github.com/chmac","contributions":1},{"login":"fearenales","html_url":"https://github.com/fearenales","contributions":1},{"login":"gfpacheco","html_url":"https://github.com/gfpacheco","contributions":1},{"login":"huyhong","html_url":"https://github.com/huyhong","contributions":1},{"login":"Ivshti","html_url":"https://github.com/Ivshti","contributions":1}]},{"name":"teammates","html_url":"https://github.com/TEAMMATES/teammates","description":"This is the project website for the TEAMMATES feedback management tool for education","pushed_at":"2017-04-19T17:29:34Z","updated_at":"2017-04-19T04:44:06Z","formatted_time":"3 minutes ago","language":"Java","stargazers_count":312,"forks_count":693,"open_issues_count":524,"size":183590,"type":"Organization","owner":{"login":"TEAMMATES","avatar_url":"https://avatars1.githubusercontent.com/u/7374810?v=3","html_url":"https://github.com/TEAMMATES"},"contributors":[{"login":"damithc","html_url":"https://github.com/damithc","contributions":1855},{"login":"kanghj","html_url":"https://github.com/kanghj","contributions":1381},{"login":"wkurniawan07","html_url":"https://github.com/wkurniawan07","contributions":1367},{"login":"LowWeiLin","html_url":"https://github.com/LowWeiLin","contributions":1152},{"login":"franklingu","html_url":"https://github.com/franklingu","contributions":881},{"login":"thyageshm","html_url":"https://github.com/thyageshm","contributions":874},{"login":"junhaoyap","html_url":"https://github.com/junhaoyap","contributions":773},{"login":"taniach","html_url":"https://github.com/taniach","contributions":669},{"login":"JosephineKwa","html_url":"https://github.com/JosephineKwa","contributions":662},{"login":"imouto1994","html_url":"https://github.com/imouto1994","contributions":627},{"login":"kai33","html_url":"https://github.com/kai33","contributions":575},{"login":"bamboo3250","html_url":"https://github.com/bamboo3250","contributions":570},{"login":"kennho","html_url":"https://github.com/kennho","contributions":438},{"login":"ymoctavia","html_url":"https://github.com/ymoctavia","contributions":428},{"login":"yj-soh","html_url":"https://github.com/yj-soh","contributions":315},{"login":"invalid-email-address","html_url":"https://github.com/invalid-email-address","contributions":272},{"login":"chunteck","html_url":"https://github.com/chunteck","contributions":226},{"login":"YongJieYongJie","html_url":"https://github.com/YongJieYongJie","contributions":190},{"login":"ackoroa","html_url":"https://github.com/ackoroa","contributions":183},{"login":"rcyq","html_url":"https://github.com/rcyq","contributions":147},{"login":"unyoungwax","html_url":"https://github.com/unyoungwax","contributions":140},{"login":"leeshawn89","html_url":"https://github.com/leeshawn89","contributions":132},{"login":"tarun14110","html_url":"https://github.com/tarun14110","contributions":127},{"login":"jamesdam","html_url":"https://github.com/jamesdam","contributions":97},{"login":"jkt001","html_url":"https://github.com/jkt001","contributions":93},{"login":"Sumei1009","html_url":"https://github.com/Sumei1009","contributions":92},{"login":"wangsha","html_url":"https://github.com/wangsha","contributions":87},{"login":"justhalf","html_url":"https://github.com/justhalf","contributions":78},{"login":"ashrayjain","html_url":"https://github.com/ashrayjain","contributions":73},{"login":"xialin","html_url":"https://github.com/xialin","contributions":45}]},{"name":"metalsmith-react-templates","html_url":"https://github.com/yeojz/metalsmith-react-templates","description":"A metalsmith plugin to render files using ReactJS based templates.","pushed_at":"2017-04-19T16:07:07Z","updated_at":"2017-04-11T15:26:31Z","formatted_time":"an hour ago","language":"JavaScript","stargazers_count":71,"forks_count":14,"open_issues_count":0,"size":239,"type":"User","owner":{"login":"yeojz","avatar_url":"https://avatars1.githubusercontent.com/u/429598?v=3","html_url":"https://github.com/yeojz"},"contributors":[{"login":"yeojz","html_url":"https://github.com/yeojz","contributions":185},{"login":"pumpikano","html_url":"https://github.com/pumpikano","contributions":2},{"login":"woodyrew","html_url":"https://github.com/woodyrew","contributions":2},{"login":"LegNeato","html_url":"https://github.com/LegNeato","contributions":1},{"login":"jonathanewerner","html_url":"https://github.com/jonathanewerner","contributions":1},{"login":"yangshun","html_url":"https://github.com/yangshun","contributions":1},{"login":"tscanlin","html_url":"https://github.com/tscanlin","contributions":1},{"login":"juhaelee","html_url":"https://github.com/juhaelee","contributions":1}]},{"name":"nlvm","html_url":"https://github.com/arnetheduck/nlvm","description":"LLVM-based compiler for the Nim language","pushed_at":"2017-04-19T15:53:11Z","updated_at":"2017-04-14T13:11:07Z","formatted_time":"2 hours ago","language":"Nim","stargazers_count":62,"forks_count":6,"open_issues_count":1,"size":366,"type":"User","owner":{"login":"arnetheduck","avatar_url":"https://avatars0.githubusercontent.com/u/1382986?v=3","html_url":"https://github.com/arnetheduck"},"contributors":[{"login":"arnetheduck","html_url":"https://github.com/arnetheduck","contributions":70}]},{"name":"inoERP","html_url":"https://github.com/inoerp/inoERP","description":"inoERP is a PHP-based open source enterprise management system that can be used with several databases - such as Oracle 12c, MariaDB, MySQL. The ERP system contains all the functionalities required for running any manufacturing, service or distribution organization. The features are very similar to Oracle R12/ Fusion Application and SAP. It also contains a lightweight CMS, which seamlessly integrates with the ERP system","pushed_at":"2017-04-19T15:25:44Z","updated_at":"2017-04-13T03:05:10Z","formatted_time":"2 hours ago","language":"PHP","stargazers_count":249,"forks_count":329,"open_issues_count":26,"size":77693,"type":"User","owner":{"login":"inoerp","avatar_url":"https://avatars1.githubusercontent.com/u/6542612?v=3","html_url":"https://github.com/inoerp"},"contributors":[{"login":"inoerp","html_url":"https://github.com/inoerp","contributions":922},{"login":"evanbuck80","html_url":"https://github.com/evanbuck80","contributions":1}]},{"name":"SkylinkJS","html_url":"https://github.com/Temasys/SkylinkJS","description":"SkylinkJS Javascript WebRTC SDK","pushed_at":"2017-04-19T12:46:32Z","updated_at":"2017-03-31T09:19:10Z","formatted_time":"5 hours ago","language":"JavaScript","stargazers_count":202,"forks_count":35,"open_issues_count":8,"size":42967,"type":"Organization","owner":{"login":"Temasys","avatar_url":"https://avatars1.githubusercontent.com/u/6687728?v=3","html_url":"https://github.com/Temasys"},"contributors":[{"login":"letchoo","html_url":"https://github.com/letchoo","contributions":1607},{"login":"tienthanh8490","html_url":"https://github.com/tienthanh8490","contributions":182},{"login":"francoisTemasys","html_url":"https://github.com/francoisTemasys","contributions":43},{"login":"serrynaimo","html_url":"https://github.com/serrynaimo","contributions":32},{"login":"agouaillard","html_url":"https://github.com/agouaillard","contributions":29},{"login":"ncurrier","html_url":"https://github.com/ncurrier","contributions":12},{"login":"JulienMuzeau","html_url":"https://github.com/JulienMuzeau","contributions":6},{"login":"johache","html_url":"https://github.com/johache","contributions":4},{"login":"CGtemasys","html_url":"https://github.com/CGtemasys","contributions":2},{"login":"sindresorhus","html_url":"https://github.com/sindresorhus","contributions":2}]},{"name":"DeepDarkFantasy","html_url":"https://github.com/ThoughtWorksInc/DeepDarkFantasy","description":"A Programming Language for Deep Learning","pushed_at":"2017-04-19T12:24:12Z","updated_at":"2017-04-19T01:25:14Z","formatted_time":"5 hours ago","language":"Haskell","stargazers_count":278,"forks_count":38,"open_issues_count":57,"size":1871,"type":"Organization","owner":{"login":"ThoughtWorksInc","avatar_url":"https://avatars0.githubusercontent.com/u/168376?v=3","html_url":"https://github.com/ThoughtWorksInc"},"contributors":[{"login":"MarisaKirisame","html_url":"https://github.com/MarisaKirisame","contributions":438},{"login":"Atry","html_url":"https://github.com/Atry","contributions":69},{"login":"dramforever","html_url":"https://github.com/dramforever","contributions":7},{"login":"ice1000","html_url":"https://github.com/ice1000","contributions":2},{"login":"billzorn","html_url":"https://github.com/billzorn","contributions":1},{"login":"hyiltiz","html_url":"https://github.com/hyiltiz","contributions":1},{"login":"gitter-badger","html_url":"https://github.com/gitter-badger","contributions":1}]},{"name":"angular-multi-select","html_url":"https://github.com/isteven/angular-multi-select","description":"A multi select dropdown directive for AngularJS. Allows you to use HTML tags and CSS in the data. Requires only AngularJS and nothing else.","pushed_at":"2017-04-19T12:03:56Z","updated_at":"2017-04-19T13:00:09Z","formatted_time":"5 hours ago","language":"JavaScript","stargazers_count":994,"forks_count":478,"open_issues_count":113,"size":2559,"type":"User","owner":{"login":"isteven","avatar_url":"https://avatars0.githubusercontent.com/u/5432100?v=3","html_url":"https://github.com/isteven"},"contributors":[{"login":"isteven","html_url":"https://github.com/isteven","contributions":126},{"login":"buunguyen","html_url":"https://github.com/buunguyen","contributions":1},{"login":"erinwu","html_url":"https://github.com/erinwu","contributions":1},{"login":"filaruina","html_url":"https://github.com/filaruina","contributions":1},{"login":"greggroth","html_url":"https://github.com/greggroth","contributions":1},{"login":"Hypercubed","html_url":"https://github.com/Hypercubed","contributions":1},{"login":"omkarv","html_url":"https://github.com/omkarv","contributions":1},{"login":"Flextras","html_url":"https://github.com/Flextras","contributions":1},{"login":"Riggs333","html_url":"https://github.com/Riggs333","contributions":1}]},{"name":"core.matrix","html_url":"https://github.com/mikera/core.matrix","description":"core.matrix : Multi-dimensional array programming API for Clojure","pushed_at":"2017-04-19T10:25:33Z","updated_at":"2017-04-17T22:38:05Z","formatted_time":"7 hours ago","language":"Clojure","stargazers_count":503,"forks_count":91,"open_issues_count":52,"size":4846,"type":"User","owner":{"login":"mikera","avatar_url":"https://avatars3.githubusercontent.com/u/212007?v=3","html_url":"https://github.com/mikera"},"contributors":[{"login":"mikera","html_url":"https://github.com/mikera","contributions":2052},{"login":"si14","html_url":"https://github.com/si14","contributions":119},{"login":"Gerrrr","html_url":"https://github.com/Gerrrr","contributions":72},{"login":"rosejn","html_url":"https://github.com/rosejn","contributions":64},{"login":"prasant94","html_url":"https://github.com/prasant94","contributions":34},{"login":"mschuene","html_url":"https://github.com/mschuene","contributions":25},{"login":"fyquah95","html_url":"https://github.com/fyquah95","contributions":22},{"login":"grtlr","html_url":"https://github.com/grtlr","contributions":10},{"login":"mattrepl","html_url":"https://github.com/mattrepl","contributions":7},{"login":"charlesg3","html_url":"https://github.com/charlesg3","contributions":6},{"login":"bmabey","html_url":"https://github.com/bmabey","contributions":5},{"login":"tbrooks8","html_url":"https://github.com/tbrooks8","contributions":5},{"login":"keithschulze","html_url":"https://github.com/keithschulze","contributions":4},{"login":"siscia","html_url":"https://github.com/siscia","contributions":4},{"login":"japonophile","html_url":"https://github.com/japonophile","contributions":3},{"login":"danielcompton","html_url":"https://github.com/danielcompton","contributions":3},{"login":"ds923y","html_url":"https://github.com/ds923y","contributions":3},{"login":"ejackson","html_url":"https://github.com/ejackson","contributions":3},{"login":"eavgerinos","html_url":"https://github.com/eavgerinos","contributions":2},{"login":"cnuernber","html_url":"https://github.com/cnuernber","contributions":2},{"login":"dmarjenburgh","html_url":"https://github.com/dmarjenburgh","contributions":2},{"login":"munk","html_url":"https://github.com/munk","contributions":2},{"login":"shark8me","html_url":"https://github.com/shark8me","contributions":2},{"login":"mjwillson","html_url":"https://github.com/mjwillson","contributions":2},{"login":"Quantisan","html_url":"https://github.com/Quantisan","contributions":2},{"login":"fbmnds","html_url":"https://github.com/fbmnds","contributions":2},{"login":"cloojure","html_url":"https://github.com/cloojure","contributions":1},{"login":"durka","html_url":"https://github.com/durka","contributions":1},{"login":"jafingerhut","html_url":"https://github.com/jafingerhut","contributions":1},{"login":"SwamWithTurtles","html_url":"https://github.com/SwamWithTurtles","contributions":1}]},{"name":"pili-sdk-java","html_url":"https://github.com/pili-engineering/pili-sdk-java","description":"Pili Streaming Cloud server-side library for Java","pushed_at":"2017-04-19T06:34:25Z","updated_at":"2017-04-19T14:44:18Z","formatted_time":"11 hours ago","language":"Java","stargazers_count":64,"forks_count":51,"open_issues_count":10,"size":4705,"type":"Organization","owner":{"login":"pili-engineering","avatar_url":"https://avatars2.githubusercontent.com/u/9427037?v=3","html_url":"https://github.com/pili-engineering"},"contributors":[{"login":"jpxiong","html_url":"https://github.com/jpxiong","contributions":101},{"login":"longbai","html_url":"https://github.com/longbai","contributions":23},{"login":"why404","html_url":"https://github.com/why404","contributions":12},{"login":"RyanDeng","html_url":"https://github.com/RyanDeng","contributions":11},{"login":"carter2000","html_url":"https://github.com/carter2000","contributions":6},{"login":"googollee","html_url":"https://github.com/googollee","contributions":2},{"login":"shimonxin","html_url":"https://github.com/shimonxin","contributions":2},{"login":"zshbleaker","html_url":"https://github.com/zshbleaker","contributions":2},{"login":"wangtuanjie","html_url":"https://github.com/wangtuanjie","contributions":2}]},{"name":"Play-with-Algorithms","html_url":"https://github.com/liuyubobobo/Play-with-Algorithms","description":"Code of my MOOC Course <Play with Algorihms>. 我在慕课网上的课程《算法与数据结构》示例代码及相关更新。","pushed_at":"2017-04-19T05:37:57Z","updated_at":"2017-04-19T00:27:28Z","formatted_time":"12 hours ago","language":"C++","stargazers_count":170,"forks_count":100,"open_issues_count":0,"size":42083,"type":"User","owner":{"login":"liuyubobobo","avatar_url":"https://avatars2.githubusercontent.com/u/2057443?v=3","html_url":"https://github.com/liuyubobobo"},"contributors":[{"login":"liuyubobobo","html_url":"https://github.com/liuyubobobo","contributions":108}]},{"name":"koel","html_url":"https://github.com/phanan/koel","description":"A personal music streaming server that works.","pushed_at":"2017-04-19T04:27:06Z","updated_at":"2017-04-19T09:30:40Z","formatted_time":"13 hours ago","language":"PHP","stargazers_count":7485,"forks_count":724,"open_issues_count":25,"size":3248,"type":"User","owner":{"login":"phanan","avatar_url":"https://avatars0.githubusercontent.com/u/8056274?v=3","html_url":"https://github.com/phanan"},"contributors":[{"login":"phanan","html_url":"https://github.com/phanan","contributions":902},{"login":"alex-phillips","html_url":"https://github.com/alex-phillips","contributions":9},{"login":"pedroborges","html_url":"https://github.com/pedroborges","contributions":8},{"login":"X-Ryl669","html_url":"https://github.com/X-Ryl669","contributions":6},{"login":"rundef","html_url":"https://github.com/rundef","contributions":4},{"login":"caffinatedmonkey","html_url":"https://github.com/caffinatedmonkey","contributions":3},{"login":"mattstauffer","html_url":"https://github.com/mattstauffer","contributions":3},{"login":"Magnifisite","html_url":"https://github.com/Magnifisite","contributions":3},{"login":"Dogfalo","html_url":"https://github.com/Dogfalo","contributions":2},{"login":"christ0ph3r","html_url":"https://github.com/christ0ph3r","contributions":2},{"login":"funcoding","html_url":"https://github.com/funcoding","contributions":2},{"login":"MelonSmasher","html_url":"https://github.com/MelonSmasher","contributions":1},{"login":"bartlomieju","html_url":"https://github.com/bartlomieju","contributions":1},{"login":"brett-anderson","html_url":"https://github.com/brett-anderson","contributions":1},{"login":"daniele-athome","html_url":"https://github.com/daniele-athome","contributions":1},{"login":"hultberg","html_url":"https://github.com/hultberg","contributions":1},{"login":"henriquebremenkanp","html_url":"https://github.com/henriquebremenkanp","contributions":1},{"login":"joanfont","html_url":"https://github.com/joanfont","contributions":1},{"login":"kerwynrg","html_url":"https://github.com/kerwynrg","contributions":1},{"login":"mattsches","html_url":"https://github.com/mattsches","contributions":1},{"login":"PeterDaveHello","html_url":"https://github.com/PeterDaveHello","contributions":1},{"login":"NamPNQ","html_url":"https://github.com/NamPNQ","contributions":1},{"login":"piamancini","html_url":"https://github.com/piamancini","contributions":1},{"login":"icewind1991","html_url":"https://github.com/icewind1991","contributions":1},{"login":"tcyrus","html_url":"https://github.com/tcyrus","contributions":1},{"login":"UrbanCMC","html_url":"https://github.com/UrbanCMC","contributions":1},{"login":"wesleybliss","html_url":"https://github.com/wesleybliss","contributions":1},{"login":"XavRsl","html_url":"https://github.com/XavRsl","contributions":1},{"login":"panzarino","html_url":"https://github.com/panzarino","contributions":1},{"login":"lbausch","html_url":"https://github.com/lbausch","contributions":1}]},{"name":"ImageGlass","html_url":"https://github.com/d2phap/ImageGlass","description":"Free and open source image viewer","pushed_at":"2017-04-19T03:47:01Z","updated_at":"2017-04-19T09:00:59Z","formatted_time":"14 hours ago","language":"C#","stargazers_count":286,"forks_count":59,"open_issues_count":43,"size":216591,"type":"User","owner":{"login":"d2phap","avatar_url":"https://avatars2.githubusercontent.com/u/3154213?v=3","html_url":"https://github.com/d2phap"},"contributors":[{"login":"d2phap","html_url":"https://github.com/d2phap","contributions":83},{"login":"dimaaan","html_url":"https://github.com/dimaaan","contributions":17},{"login":"Baegus","html_url":"https://github.com/Baegus","contributions":2},{"login":"fire-eggs","html_url":"https://github.com/fire-eggs","contributions":2},{"login":"ToFran","html_url":"https://github.com/ToFran","contributions":1},{"login":"keedi","html_url":"https://github.com/keedi","contributions":1},{"login":"Lonami","html_url":"https://github.com/Lonami","contributions":1},{"login":"m1ga","html_url":"https://github.com/m1ga","contributions":1},{"login":"thesauri","html_url":"https://github.com/thesauri","contributions":1}]},{"name":"npm-programmatic","html_url":"https://github.com/Manak/npm-programmatic","description":"npm-programmatic is a library that allows you to access npm commands programmatically from javascript","pushed_at":"2017-04-18T18:18:13Z","updated_at":"2017-03-03T06:04:22Z","formatted_time":"a day ago","language":"JavaScript","stargazers_count":63,"forks_count":9,"open_issues_count":4,"size":12,"type":"User","owner":{"login":"Manak","avatar_url":"https://avatars2.githubusercontent.com/u/1011049?v=3","html_url":"https://github.com/Manak"},"contributors":[{"login":"Manak","html_url":"https://github.com/Manak","contributions":25},{"login":"donothingloop","html_url":"https://github.com/donothingloop","contributions":2}]}]}