{"meta":{"generated_at":"2015-03-17T18:35:58.862Z","location":"Singapore","total_repos":1,"api_version":"v1","max_users":1000,"max_repos":50},"repos":[{"name":"amazon-ecs","html_url":"https://github.com/jugend/amazon-ecs","description":"Generic Ruby Amazon Product Advertising API","pushed_at":"2015-03-16T15:27:53Z","updated_at":"2015-03-16T15:27:54Z","language":"Ruby","stargazers_count":365,"owner":{"login":"jugend","avatar_url":"https://avatars.githubusercontent.com/u/7715?v=3","html_url":"https://github.com/jugend"}}]}