{"meta":{"generated_at":"2018-03-06T02:04:19.969Z","location":"Singapore","total_repos":15},"repos":[{"name":"2018.fossasia.org","html_url":"https://github.com/fossasia/2018.fossasia.org","description":"FOSSASIA Summit 2018 https://2018.fossasia.org","pushed_at":"2018-03-06T01:56:21Z","updated_at":"2018-03-05T08:20:57Z","formatted_time":"4 minutes ago","language":"HTML","stargazers_count":337,"forks_count":149,"open_issues_count":11,"size":88721,"type":"Organization","owner":{"login":"fossasia","avatar_url":"https://avatars3.githubusercontent.com/u/6295529?v=4","html_url":"https://github.com/fossasia"},"contributors":[{"login":"hpdang","html_url":"https://github.com/hpdang","contributions":95},{"login":"mariobehling","html_url":"https://github.com/mariobehling","contributions":65},{"login":"achiv","html_url":"https://github.com/achiv","contributions":56},{"login":"gautamjajoo","html_url":"https://github.com/gautamjajoo","contributions":29},{"login":"simsausaurabh","html_url":"https://github.com/simsausaurabh","contributions":28},{"login":"nityanandagohain","html_url":"https://github.com/nityanandagohain","contributions":19},{"login":"mengjiann","html_url":"https://github.com/mengjiann","contributions":14},{"login":"rishabh19038","html_url":"https://github.com/rishabh19038","contributions":14},{"login":"niccokunzmann","html_url":"https://github.com/niccokunzmann","contributions":13},{"login":"ritikamotwani","html_url":"https://github.com/ritikamotwani","contributions":10},{"login":"dishant-sheth","html_url":"https://github.com/dishant-sheth","contributions":9},{"login":"meets2tarun","html_url":"https://github.com/meets2tarun","contributions":7},{"login":"samyukthacodes","html_url":"https://github.com/samyukthacodes","contributions":6},{"login":"prshntsingh","html_url":"https://github.com/prshntsingh","contributions":6},{"login":"AshishkrGoyal","html_url":"https://github.com/AshishkrGoyal","contributions":5},{"login":"apooravc","html_url":"https://github.com/apooravc","contributions":4},{"login":"downeym","html_url":"https://github.com/downeym","contributions":4},{"login":"parimatrix","html_url":"https://github.com/parimatrix","contributions":4},{"login":"the-dagger","html_url":"https://github.com/the-dagger","contributions":3},{"login":"naokichau","html_url":"https://github.com/naokichau","contributions":3},{"login":"PrP-11","html_url":"https://github.com/PrP-11","contributions":3},{"login":"sayak119","html_url":"https://github.com/sayak119","contributions":3},{"login":"Apex1000","html_url":"https://github.com/Apex1000","contributions":3},{"login":"rupav","html_url":"https://github.com/rupav","contributions":3},{"login":"duttaditya18","html_url":"https://github.com/duttaditya18","contributions":2},{"login":"olttwa","html_url":"https://github.com/olttwa","contributions":2},{"login":"architkshk","html_url":"https://github.com/architkshk","contributions":2},{"login":"kubami9","html_url":"https://github.com/kubami9","contributions":2},{"login":"himanish-star","html_url":"https://github.com/himanish-star","contributions":2},{"login":"Tanuj9043","html_url":"https://github.com/Tanuj9043","contributions":2}]},{"name":"telegram-bot","html_url":"https://github.com/lesterchan/telegram-bot","description":"Telegram Bot using AWS API Gateway and AWS Lamda","pushed_at":"2018-03-06T01:24:31Z","updated_at":"2018-03-02T19:28:58Z","formatted_time":"4 minutes ago","language":"JavaScript","stargazers_count":54,"forks_count":9,"open_issues_count":0,"size":40,"type":"User","owner":{"login":"lesterchan","avatar_url":"https://avatars2.githubusercontent.com/u/355829?v=4","html_url":"https://github.com/lesterchan"},"contributors":[{"login":"lesterchan","html_url":"https://github.com/lesterchan","contributions":22}]},{"name":"nusmods","html_url":"https://github.com/nusmodifications/nusmods","description":"🏫 Unofficial course planning platform for National University of Singapore.","pushed_at":"2018-03-06T00:33:24Z","updated_at":"2018-03-05T07:20:55Z","formatted_time":"an hour ago","language":"JavaScript","stargazers_count":181,"forks_count":94,"open_issues_count":74,"size":10530,"type":"Organization","owner":{"login":"nusmodifications","avatar_url":"https://avatars3.githubusercontent.com/u/7428865?v=4","html_url":"https://github.com/nusmodifications"},"contributors":[{"login":"yangshun","html_url":"https://github.com/yangshun","contributions":900},{"login":"ahbeng","html_url":"https://github.com/ahbeng","contributions":814},{"login":"ZhangYiJiang","html_url":"https://github.com/ZhangYiJiang","contributions":141},{"login":"li-kai","html_url":"https://github.com/li-kai","contributions":136},{"login":"ngzhian","html_url":"https://github.com/ngzhian","contributions":75},{"login":"xinan","html_url":"https://github.com/xinan","contributions":67},{"login":"taneliang","html_url":"https://github.com/taneliang","contributions":35},{"login":"ashrayjain","html_url":"https://github.com/ashrayjain","contributions":31},{"login":"xbili","html_url":"https://github.com/xbili","contributions":27},{"login":"zhouyichen","html_url":"https://github.com/zhouyichen","contributions":14},{"login":"xming13","html_url":"https://github.com/xming13","contributions":8},{"login":"chunqi","html_url":"https://github.com/chunqi","contributions":7},{"login":"karen","html_url":"https://github.com/karen","contributions":6},{"login":"zameschua","html_url":"https://github.com/zameschua","contributions":6},{"login":"mauris","html_url":"https://github.com/mauris","contributions":5},{"login":"tgxworld","html_url":"https://github.com/tgxworld","contributions":4},{"login":"hong-lu","html_url":"https://github.com/hong-lu","contributions":4},{"login":"Yunheng","html_url":"https://github.com/Yunheng","contributions":4},{"login":"nicholette","html_url":"https://github.com/nicholette","contributions":4},{"login":"kennetham","html_url":"https://github.com/kennetham","contributions":3},{"login":"angelsl","html_url":"https://github.com/angelsl","contributions":3},{"login":"JishnuM","html_url":"https://github.com/JishnuM","contributions":2},{"login":"hanlindev","html_url":"https://github.com/hanlindev","contributions":2},{"login":"shanwpf","html_url":"https://github.com/shanwpf","contributions":2},{"login":"franklingu","html_url":"https://github.com/franklingu","contributions":2},{"login":"jin","html_url":"https://github.com/jin","contributions":2},{"login":"arsalanc-v2","html_url":"https://github.com/arsalanc-v2","contributions":1},{"login":"davis12529","html_url":"https://github.com/davis12529","contributions":1},{"login":"nexolute","html_url":"https://github.com/nexolute","contributions":1},{"login":"kiangkuang","html_url":"https://github.com/kiangkuang","contributions":1}]},{"name":"HelpHub","html_url":"https://github.com/Kenshino/HelpHub","description":"The WordPress user documentation portal","pushed_at":"2018-03-06T00:22:07Z","updated_at":"2018-03-05T14:32:22Z","formatted_time":"an hour ago","language":"CSS","stargazers_count":50,"forks_count":25,"open_issues_count":16,"size":1969,"type":"User","owner":{"login":"Kenshino","avatar_url":"https://avatars3.githubusercontent.com/u/4746365?v=4","html_url":"https://github.com/Kenshino"},"contributors":[{"login":"Kenshino","html_url":"https://github.com/Kenshino","contributions":65},{"login":"justingreerbbi","html_url":"https://github.com/justingreerbbi","contributions":53},{"login":"zzap","html_url":"https://github.com/zzap","contributions":34},{"login":"ntwb","html_url":"https://github.com/ntwb","contributions":31},{"login":"miya0001","html_url":"https://github.com/miya0001","contributions":27},{"login":"hlashbrooke","html_url":"https://github.com/hlashbrooke","contributions":13},{"login":"carl-alberto","html_url":"https://github.com/carl-alberto","contributions":6},{"login":"Clorith","html_url":"https://github.com/Clorith","contributions":5},{"login":"atachibana","html_url":"https://github.com/atachibana","contributions":3},{"login":"torounit","html_url":"https://github.com/torounit","contributions":3},{"login":"mapk","html_url":"https://github.com/mapk","contributions":3},{"login":"joyously","html_url":"https://github.com/joyously","contributions":2},{"login":"mathetos","html_url":"https://github.com/mathetos","contributions":2},{"login":"mariovalney","html_url":"https://github.com/mariovalney","contributions":1},{"login":"bravokeyl","html_url":"https://github.com/bravokeyl","contributions":1},{"login":"hideokamoto","html_url":"https://github.com/hideokamoto","contributions":1},{"login":"Mirucon","html_url":"https://github.com/Mirucon","contributions":1}]},{"name":"react-native-credit-card-input","html_url":"https://github.com/sbycrosz/react-native-credit-card-input","description":"Easy, cross-platform credit-card input for your React Native Project! Start accepting payment 💰 in your app today!","pushed_at":"2018-03-05T23:04:35Z","updated_at":"2018-03-05T06:24:53Z","formatted_time":"2 hours ago","language":"JavaScript","stargazers_count":568,"forks_count":188,"open_issues_count":28,"size":1581,"type":"User","owner":{"login":"sbycrosz","avatar_url":"https://avatars3.githubusercontent.com/u/4867178?v=4","html_url":"https://github.com/sbycrosz"},"contributors":[{"login":"sbycrosz","html_url":"https://github.com/sbycrosz","contributions":92},{"login":"CooLSeS","html_url":"https://github.com/CooLSeS","contributions":2},{"login":"wchaering","html_url":"https://github.com/wchaering","contributions":2},{"login":"Andreyco","html_url":"https://github.com/Andreyco","contributions":1},{"login":"kraffslol","html_url":"https://github.com/kraffslol","contributions":1},{"login":"sscaff1","html_url":"https://github.com/sscaff1","contributions":1}]},{"name":"machinery","html_url":"https://github.com/RichardKnop/machinery","description":"Machinery is an asynchronous task queue/job queue based on distributed message passing.","pushed_at":"2018-03-05T22:45:18Z","updated_at":"2018-03-05T01:02:05Z","formatted_time":"3 hours ago","language":"Go","stargazers_count":2048,"forks_count":237,"open_issues_count":22,"size":17690,"type":"User","owner":{"login":"RichardKnop","avatar_url":"https://avatars0.githubusercontent.com/u/2325888?v=4","html_url":"https://github.com/RichardKnop"},"contributors":[{"login":"RichardKnop","html_url":"https://github.com/RichardKnop","contributions":485},{"login":"ZhenhangTung","html_url":"https://github.com/ZhenhangTung","contributions":28},{"login":"mjetpax","html_url":"https://github.com/mjetpax","contributions":19},{"login":"ItsLeeOwen","html_url":"https://github.com/ItsLeeOwen","contributions":19},{"login":"Rio","html_url":"https://github.com/Rio","contributions":12},{"login":"surendratiwari3","html_url":"https://github.com/surendratiwari3","contributions":9},{"login":"ConnorDoyle","html_url":"https://github.com/ConnorDoyle","contributions":4},{"login":"WillAbides","html_url":"https://github.com/WillAbides","contributions":4},{"login":"evolsnow","html_url":"https://github.com/evolsnow","contributions":4},{"login":"requilence","html_url":"https://github.com/requilence","contributions":4},{"login":"xtzhangfw","html_url":"https://github.com/xtzhangfw","contributions":4},{"login":"apostov","html_url":"https://github.com/apostov","contributions":3},{"login":"codepushr","html_url":"https://github.com/codepushr","contributions":2},{"login":"justinhillsjohnson","html_url":"https://github.com/justinhillsjohnson","contributions":2},{"login":"kenkouot","html_url":"https://github.com/kenkouot","contributions":2},{"login":"parhamdoustdar","html_url":"https://github.com/parhamdoustdar","contributions":2},{"login":"pauldevelder","html_url":"https://github.com/pauldevelder","contributions":2},{"login":"nytr0gen","html_url":"https://github.com/nytr0gen","contributions":2},{"login":"denkhaus","html_url":"https://github.com/denkhaus","contributions":2},{"login":"vkd","html_url":"https://github.com/vkd","contributions":2},{"login":"jurre","html_url":"https://github.com/jurre","contributions":2},{"login":"2tvenom","html_url":"https://github.com/2tvenom","contributions":1},{"login":"masnun","html_url":"https://github.com/masnun","contributions":1},{"login":"ankurs","html_url":"https://github.com/ankurs","contributions":1},{"login":"becoded","html_url":"https://github.com/becoded","contributions":1},{"login":"deiwin","html_url":"https://github.com/deiwin","contributions":1},{"login":"yoloseem","html_url":"https://github.com/yoloseem","contributions":1},{"login":"vano468","html_url":"https://github.com/vano468","contributions":1},{"login":"niedbalski","html_url":"https://github.com/niedbalski","contributions":1},{"login":"kartlee","html_url":"https://github.com/kartlee","contributions":1}]},{"name":"teammates","html_url":"https://github.com/TEAMMATES/teammates","description":"This is the project website for the TEAMMATES feedback management tool for education","pushed_at":"2018-03-05T21:58:38Z","updated_at":"2018-03-04T17:17:46Z","formatted_time":"4 hours ago","language":"Java","stargazers_count":557,"forks_count":1313,"open_issues_count":283,"size":195360,"type":"Organization","owner":{"login":"TEAMMATES","avatar_url":"https://avatars2.githubusercontent.com/u/7374810?v=4","html_url":"https://github.com/TEAMMATES"},"contributors":[{"login":"damithc","html_url":"https://github.com/damithc","contributions":1858},{"login":"wkurniawan07","html_url":"https://github.com/wkurniawan07","contributions":1402},{"login":"kanghj","html_url":"https://github.com/kanghj","contributions":1381},{"login":"LowWeiLin","html_url":"https://github.com/LowWeiLin","contributions":1152},{"login":"franklingu","html_url":"https://github.com/franklingu","contributions":881},{"login":"thyageshm","html_url":"https://github.com/thyageshm","contributions":874},{"login":"junhaoyap","html_url":"https://github.com/junhaoyap","contributions":773},{"login":"taniach","html_url":"https://github.com/taniach","contributions":669},{"login":"JosephineKwa","html_url":"https://github.com/JosephineKwa","contributions":662},{"login":"imouto1994","html_url":"https://github.com/imouto1994","contributions":627},{"login":"kai33","html_url":"https://github.com/kai33","contributions":575},{"login":"bamboo3250","html_url":"https://github.com/bamboo3250","contributions":570},{"login":"kennho","html_url":"https://github.com/kennho","contributions":438},{"login":"ymoctavia","html_url":"https://github.com/ymoctavia","contributions":428},{"login":"yj-soh","html_url":"https://github.com/yj-soh","contributions":315},{"login":"invalid-email-address","html_url":"https://github.com/invalid-email-address","contributions":272},{"login":"chunteck","html_url":"https://github.com/chunteck","contributions":226},{"login":"YongJieYongJie","html_url":"https://github.com/YongJieYongJie","contributions":190},{"login":"ackoroa","html_url":"https://github.com/ackoroa","contributions":183},{"login":"ryancyq","html_url":"https://github.com/ryancyq","contributions":146},{"login":"unyoungwax","html_url":"https://github.com/unyoungwax","contributions":140},{"login":"leeshawn89","html_url":"https://github.com/leeshawn89","contributions":132},{"login":"tarun14110","html_url":"https://github.com/tarun14110","contributions":127},{"login":"jamesdam","html_url":"https://github.com/jamesdam","contributions":97},{"login":"whipermr5","html_url":"https://github.com/whipermr5","contributions":96},{"login":"jkt001","html_url":"https://github.com/jkt001","contributions":93},{"login":"Sumei1009","html_url":"https://github.com/Sumei1009","contributions":92},{"login":"wangsha","html_url":"https://github.com/wangsha","contributions":87},{"login":"justhalf","html_url":"https://github.com/justhalf","contributions":78},{"login":"ashrayjain","html_url":"https://github.com/ashrayjain","contributions":73}]},{"name":"create-react-app-now","html_url":"https://github.com/xkawi/create-react-app-now","description":"Hello, create-react-app, meet Zeit's awesome now.sh service.","pushed_at":"2018-03-05T18:24:52Z","updated_at":"2018-02-26T06:31:59Z","formatted_time":"7 hours ago","language":"JavaScript","stargazers_count":129,"forks_count":6,"open_issues_count":8,"size":50,"type":"User","owner":{"login":"xkawi","avatar_url":"https://avatars3.githubusercontent.com/u/7726233?v=4","html_url":"https://github.com/xkawi"},"contributors":[{"login":"xkawi","html_url":"https://github.com/xkawi","contributions":41},{"login":"goldensunliu","html_url":"https://github.com/goldensunliu","contributions":1}]},{"name":"basic-yolo-keras","html_url":"https://github.com/experiencor/basic-yolo-keras","description":"Easy training on custom dataset. Various backends (MobileNet and SqueezeNet) supported. A YOLO demo to detect raccoon run entirely in brower is accessible at https://git.io/vF7vI (not on Windows).","pushed_at":"2018-03-05T14:00:11Z","updated_at":"2018-03-06T00:57:05Z","formatted_time":"11 hours ago","language":"Jupyter Notebook","stargazers_count":475,"forks_count":198,"open_issues_count":53,"size":53386,"type":"User","owner":{"login":"experiencor","avatar_url":"https://avatars1.githubusercontent.com/u/5645503?v=4","html_url":"https://github.com/experiencor"},"contributors":[{"login":"experiencor","html_url":"https://github.com/experiencor","contributions":56},{"login":"alanjschoen","html_url":"https://github.com/alanjschoen","contributions":1},{"login":"hobson","html_url":"https://github.com/hobson","contributions":1},{"login":"sirotenko","html_url":"https://github.com/sirotenko","contributions":1},{"login":"NPetsky","html_url":"https://github.com/NPetsky","contributions":1},{"login":"aspentechlabs","html_url":"https://github.com/aspentechlabs","contributions":1},{"login":"mrshu","html_url":"https://github.com/mrshu","contributions":1},{"login":"usatenko","html_url":"https://github.com/usatenko","contributions":1}]},{"name":"flask-limiter","html_url":"https://github.com/alisaifee/flask-limiter","description":"rate limiting extension for flask applications","pushed_at":"2018-03-05T13:28:42Z","updated_at":"2018-03-02T02:15:29Z","formatted_time":"12 hours ago","language":"Python","stargazers_count":290,"forks_count":43,"open_issues_count":16,"size":584,"type":"User","owner":{"login":"alisaifee","avatar_url":"https://avatars1.githubusercontent.com/u/79842?v=4","html_url":"https://github.com/alisaifee"},"contributors":[{"login":"alisaifee","html_url":"https://github.com/alisaifee","contributions":336},{"login":"joshfriend","html_url":"https://github.com/joshfriend","contributions":7},{"login":"RobertDeRose","html_url":"https://github.com/RobertDeRose","contributions":3},{"login":"themalkolm","html_url":"https://github.com/themalkolm","contributions":2},{"login":"Smashman","html_url":"https://github.com/Smashman","contributions":2},{"login":"g-p-g","html_url":"https://github.com/g-p-g","contributions":2},{"login":"henningpeters","html_url":"https://github.com/henningpeters","contributions":2},{"login":"mtsgrd","html_url":"https://github.com/mtsgrd","contributions":2},{"login":"chadlung","html_url":"https://github.com/chadlung","contributions":1},{"login":"CheeseTheMonkey","html_url":"https://github.com/CheeseTheMonkey","contributions":1},{"login":"displague","html_url":"https://github.com/displague","contributions":1},{"login":"SamiHiltunen","html_url":"https://github.com/SamiHiltunen","contributions":1},{"login":"gitter-badger","html_url":"https://github.com/gitter-badger","contributions":1},{"login":"pyup-bot","html_url":"https://github.com/pyup-bot","contributions":1}]},{"name":"Sudachi","html_url":"https://github.com/WorksApplications/Sudachi","description":"Sudachi is Japanese morphological analyzer","pushed_at":"2018-03-05T11:44:15Z","updated_at":"2018-03-03T03:45:02Z","formatted_time":"14 hours ago","language":"Java","stargazers_count":201,"forks_count":12,"open_issues_count":4,"size":479,"type":"Organization","owner":{"login":"WorksApplications","avatar_url":"https://avatars2.githubusercontent.com/u/1889132?v=4","html_url":"https://github.com/WorksApplications"},"contributors":[{"login":"kazuma-t","html_url":"https://github.com/kazuma-t","contributions":219},{"login":"KengoTODA","html_url":"https://github.com/KengoTODA","contributions":25},{"login":"sorami","html_url":"https://github.com/sorami","contributions":14},{"login":"sh0nk","html_url":"https://github.com/sh0nk","contributions":1},{"login":"ikawaha","html_url":"https://github.com/ikawaha","contributions":1},{"login":"mugenen","html_url":"https://github.com/mugenen","contributions":1}]},{"name":"TagUI","html_url":"https://github.com/tebelorg/TagUI","description":"General purpose tool for automating web interactions","pushed_at":"2018-03-05T11:41:28Z","updated_at":"2018-03-05T10:59:34Z","formatted_time":"14 hours ago","language":"JavaScript","stargazers_count":2621,"forks_count":104,"open_issues_count":4,"size":28839,"type":"Organization","owner":{"login":"tebelorg","avatar_url":"https://avatars1.githubusercontent.com/u/10379612?v=4","html_url":"https://github.com/tebelorg"},"contributors":[{"login":"kensoh","html_url":"https://github.com/kensoh","contributions":715},{"login":"gitter-badger","html_url":"https://github.com/gitter-badger","contributions":1}]},{"name":"SchoolIdolAPI","html_url":"https://github.com/MagiCircles/SchoolIdolAPI","description":"The ultimate resource for LLSIF players","pushed_at":"2018-03-05T09:49:03Z","updated_at":"2018-03-05T17:35:29Z","formatted_time":"16 hours ago","language":"Python","stargazers_count":113,"forks_count":31,"open_issues_count":125,"size":59684,"type":"Organization","owner":{"login":"MagiCircles","avatar_url":"https://avatars0.githubusercontent.com/u/11432639?v=4","html_url":"https://github.com/MagiCircles"},"contributors":[{"login":"db0company","html_url":"https://github.com/db0company","contributions":1362},{"login":"vphong","html_url":"https://github.com/vphong","contributions":31},{"login":"Engil","html_url":"https://github.com/Engil","contributions":26},{"login":"dburr","html_url":"https://github.com/dburr","contributions":15},{"login":"korfuri","html_url":"https://github.com/korfuri","contributions":6},{"login":"msmrrenda","html_url":"https://github.com/msmrrenda","contributions":5},{"login":"rdsathene","html_url":"https://github.com/rdsathene","contributions":3},{"login":"SixSonatas","html_url":"https://github.com/SixSonatas","contributions":3},{"login":"BooDoo","html_url":"https://github.com/BooDoo","contributions":1},{"login":"riseremi","html_url":"https://github.com/riseremi","contributions":1}]},{"name":"SUTDAnnotator","html_url":"https://github.com/jiesutd/SUTDAnnotator","description":"YEDDA: A Lightweight Collaborative Text Span Annotation Tool","pushed_at":"2018-03-05T09:41:17Z","updated_at":"2018-03-04T05:11:49Z","formatted_time":"16 hours ago","language":"Python","stargazers_count":68,"forks_count":24,"open_issues_count":0,"size":7511,"type":"User","owner":{"login":"jiesutd","avatar_url":"https://avatars0.githubusercontent.com/u/9111828?v=4","html_url":"https://github.com/jiesutd"},"contributors":[{"login":"jiesutd","html_url":"https://github.com/jiesutd","contributions":95}]},{"name":"vue-google-maps","html_url":"https://github.com/xkjyeah/vue-google-maps","description":"Google maps component for vue with 2-way data binding","pushed_at":"2018-03-05T07:42:43Z","updated_at":"2018-03-05T10:14:57Z","formatted_time":"18 hours ago","language":"JavaScript","stargazers_count":637,"forks_count":163,"open_issues_count":123,"size":22959,"type":"User","owner":{"login":"xkjyeah","avatar_url":"https://avatars3.githubusercontent.com/u/2659143?v=4","html_url":"https://github.com/xkjyeah"},"contributors":[{"login":"xkjyeah","html_url":"https://github.com/xkjyeah","contributions":199},{"login":"GuillaumeLeclerc","html_url":"https://github.com/GuillaumeLeclerc","contributions":128},{"login":"yyx990803","html_url":"https://github.com/yyx990803","contributions":32},{"login":"smartpierre","html_url":"https://github.com/smartpierre","contributions":7},{"login":"monsieurmechant","html_url":"https://github.com/monsieurmechant","contributions":5},{"login":"t2thec","html_url":"https://github.com/t2thec","contributions":4},{"login":"bastilimbach","html_url":"https://github.com/bastilimbach","contributions":3},{"login":"plarsson","html_url":"https://github.com/plarsson","contributions":2},{"login":"shayneo","html_url":"https://github.com/shayneo","contributions":2},{"login":"stevendesu","html_url":"https://github.com/stevendesu","contributions":2},{"login":"invalid-email-address","html_url":"https://github.com/invalid-email-address","contributions":2},{"login":"mercs600","html_url":"https://github.com/mercs600","contributions":1},{"login":"letovlive","html_url":"https://github.com/letovlive","contributions":1},{"login":"ashtonzheng","html_url":"https://github.com/ashtonzheng","contributions":1},{"login":"nothingrandom","html_url":"https://github.com/nothingrandom","contributions":1},{"login":"caiquecastro","html_url":"https://github.com/caiquecastro","contributions":1},{"login":"pushchris","html_url":"https://github.com/pushchris","contributions":1},{"login":"dccampbell","html_url":"https://github.com/dccampbell","contributions":1},{"login":"Kostandy","html_url":"https://github.com/Kostandy","contributions":1},{"login":"feliperoberto","html_url":"https://github.com/feliperoberto","contributions":1},{"login":"gpopoteur","html_url":"https://github.com/gpopoteur","contributions":1},{"login":"MinGoo-Kim","html_url":"https://github.com/MinGoo-Kim","contributions":1},{"login":"sabrinaluo","html_url":"https://github.com/sabrinaluo","contributions":1},{"login":"apertureless","html_url":"https://github.com/apertureless","contributions":1},{"login":"FranzSkuffka","html_url":"https://github.com/FranzSkuffka","contributions":1},{"login":"jlaswell","html_url":"https://github.com/jlaswell","contributions":1},{"login":"portwatcher","html_url":"https://github.com/portwatcher","contributions":1},{"login":"noevidenz","html_url":"https://github.com/noevidenz","contributions":1},{"login":"michaelhue","html_url":"https://github.com/michaelhue","contributions":1},{"login":"smhutch","html_url":"https://github.com/smhutch","contributions":1}]}]}